pdt_canny.py
pdt_extract/__init__.py
pdt_extract/feature_extract.py
pdt_extract/original_extraction_functions.py
pdt_extract/pdt_extract.py
pdt_extract-0.1.6.dist-info/METADATA
pdt_extract-0.1.6.dist-info/WHEEL
pdt_extract-0.1.6.dist-info/top_level.txt
pdt_extract-0.1.6.dist-info/RECORD
