Metadata-Version: 2.1
Name: pdt-extract
Version: 0.1.6
Summary: Perform edge profile and characteristic feature extraction from images of pendant drops
Home-page: https://github.com/DmitriLyalikov/pdt-canny-edge-detector
Author: Dmitri Lyalikov
Author-email: Dlyalikov01@manhattan.edu
Classifier: Intended Audience :: Science/Research
Requires-Dist: imageio
Requires-Dist: scipy
Requires-Dist: numpy
Requires-Dist: matplotlib
Requires-Dist: circle-fit
Requires-Dist: pandas
